findviz/__init__.py
findviz/cli.py
findviz/logger_config.py
findviz/routes/__init__.py
findviz/routes/file.py
findviz/routes/main.py
findviz/routes/shared.py
findviz/routes/utils.py
findviz/routes/viewer/analysis.py
findviz/routes/viewer/color.py
findviz/routes/viewer/data.py
findviz/routes/viewer/gifti.py
findviz/routes/viewer/io.py
findviz/routes/viewer/logs.py
findviz/routes/viewer/nifti.py
findviz/routes/viewer/plot.py
findviz/routes/viewer/preprocess.py
findviz/static/css/styles.css
findviz/static/css/vendor/all.min.css
findviz/static/css/vendor/bootstrap-select.min.css
findviz/static/css/vendor/bootstrap-slider.min.css
findviz/static/css/vendor/bootstrap.min.css
findviz/static/css/webfonts/fa-brands-400.ttf
findviz/static/css/webfonts/fa-brands-400.woff2
findviz/static/css/webfonts/fa-regular-400.ttf
findviz/static/css/webfonts/fa-regular-400.woff2
findviz/static/css/webfonts/fa-solid-900.ttf
findviz/static/css/webfonts/fa-solid-900.woff2
findviz/static/css/webfonts/fa-v4compatibility.ttf
findviz/static/css/webfonts/fa-v4compatibility.woff2
findviz/static/images/FIND.png
findviz/static/images/task_design_file.png
findviz/static/js/Spinner.js
findviz/static/js/constants/APIEndpoints.js
findviz/static/js/constants/DomIds.js
findviz/static/js/constants/EventTypes.js
findviz/static/js/log.js
findviz/static/js/main.js
findviz/static/js/upload/FileUploader.js
findviz/static/js/upload/UploadErrorHandler.js
findviz/static/js/upload/components/CiftiFileManager.js
findviz/static/js/upload/components/GiftiFileManager.js
findviz/static/js/upload/components/NiftiFileManager.js
findviz/static/js/upload/components/TRFormListener.js
findviz/static/js/upload/components/TaskDesignFileManager.js
findviz/static/js/upload/components/TimeSeriesFileManager.js
findviz/static/js/upload/components/UploadScene.js
findviz/static/js/utils.js
findviz/static/js/vendor/bootstrap-select.min.js
findviz/static/js/vendor/bootstrap-slider.min.js
findviz/static/js/vendor/bootstrap.min.js
findviz-0.1.4.dist-info/LICENSE
findviz-0.1.4.dist-info/METADATA
findviz-0.1.4.dist-info/WHEEL
findviz-0.1.4.dist-info/entry_points.txt
findviz-0.1.4.dist-info/RECORD
