Metadata-Version: 2.1
Name: findviz
Version: 0.1.4
Summary: FIND Viewer: FMRI Interactive Navigation and Discovery Viewer
Home-page: https://github.com/tsb46/fmri-findviz
License: MIT
Keywords: fmri,neuroimaging,visualization,neuroscience
Author: Taylor Bolt
Author-email: taylor.s.bolt@gmail.com
Requires-Python: >=3.10,<4.0
Classifier: Intended Audience :: Science/Research
Classifier: License :: OSI Approved :: MIT License
Classifier: Programming Language :: Python :: 3
Classifier: Programming Language :: Python :: 3.10
Classifier: Programming Language :: Python :: 3.11
Classifier: Topic :: Scientific/Engineering :: Medical Science Apps.
Requires-Dist: Flask (==3.0.3)
Requires-Dist: matplotlib (==3.9.2)
Requires-Dist: nilearn (==0.10.4)
Requires-Dist: plotly (==5.23.0)
Project-URL: Repository, https://github.com/tsb46/fmri-findviz
